nullstools/NullsMod.py
nullstools/__init__.py
nullstools-0.1.4.dist-info/LICENSE
nullstools-0.1.4.dist-info/METADATA
nullstools-0.1.4.dist-info/WHEEL
nullstools-0.1.4.dist-info/top_level.txt
nullstools-0.1.4.dist-info/RECORD
